quickmin_step/__init__.py
quickmin_step/_version.py
quickmin_step/metadata.py
quickmin_step/quickmin.py
quickmin_step/quickmin_parameters.py
quickmin_step/quickmin_step.py
quickmin_step/tk_quickmin.py
quickmin_step/data/properties.csv
quickmin_step/data/references.bib
quickmin_step-2025.2.24.dist-info/AUTHORS.rst
quickmin_step-2025.2.24.dist-info/LICENSE
quickmin_step-2025.2.24.dist-info/METADATA
quickmin_step-2025.2.24.dist-info/WHEEL
quickmin_step-2025.2.24.dist-info/entry_points.txt
quickmin_step-2025.2.24.dist-info/top_level.txt
quickmin_step-2025.2.24.dist-info/zip-safe
quickmin_step-2025.2.24.dist-info/RECORD
